dataanalysistoolkit/.conf/plot_config.json
dataanalysistoolkit/__init__.py
dataanalysistoolkit/data_analysis_toolkit.py
dataanalysistoolkit/data_sources/__init__.py
dataanalysistoolkit/data_sources/api_connector.py
dataanalysistoolkit/data_sources/excel_connector.py
dataanalysistoolkit/data_sources/sql_connector.py
dataanalysistoolkit/formatters/__init__.py
dataanalysistoolkit/formatters/data_formatter.py
dataanalysistoolkit/generators/__init__.py
dataanalysistoolkit/generators/csv_data_generator.py
dataanalysistoolkit/generators/generate_data.py
dataanalysistoolkit/generators/report_generator.py
dataanalysistoolkit/integrators/__init__.py
dataanalysistoolkit/integrators/data_integrator.py
dataanalysistoolkit/model/__init__.py
dataanalysistoolkit/model/feature_engineer.py
dataanalysistoolkit/model/model_evaluator.py
dataanalysistoolkit/preprocessor/__init__.py
dataanalysistoolkit/preprocessor/data_prep.py
dataanalysistoolkit/utils/__init__.py
dataanalysistoolkit/utils/data_imputer.py
dataanalysistoolkit/visualizer/__init__.py
dataanalysistoolkit/visualizer/data_visualizer.py
tests/data/gen_test.csv
tests/data/test_random.csv
dataanalysistoolkit-1.2.2.dist-info/METADATA
dataanalysistoolkit-1.2.2.dist-info/WHEEL
dataanalysistoolkit-1.2.2.dist-info/RECORD
