Metadata-Version: 2.1
Name: DataAnalysisToolkit
Version: 1.2.2
Summary: The DataAnalysisToolkit project is a Python-based data analysis tool designed to streamline various data analysis tasks. It allows users to load data from CSV files and perform operations such as statistical calculations, outlier detection, data cleaning, and visualization.
Home-page: https://github.com/thomasthaddeus/dataanalysistoolkit
License: MIT
Keywords: data analysis,CSV,statistics,data cleaning,data visualization
Author: Thaddeus Thomas
Author-email: thaddeus.r.thomas@gmail.com
Requires-Python: >=3.9,<4.0
Classifier: Development Status :: 4 - Beta
Classifier: Environment :: Console
Classifier: Framework :: Jupyter
Classifier: Intended Audience :: Education
Classifier: Intended Audience :: End Users/Desktop
Classifier: License :: OSI Approved :: MIT License
Classifier: Operating System :: OS Independent
Classifier: Programming Language :: Python :: 3
Classifier: Programming Language :: Python :: 3.9
Classifier: Programming Language :: Python :: 3.10
Classifier: Programming Language :: Python :: 3.11
Classifier: Programming Language :: Python :: 3.12
Classifier: Topic :: Scientific/Engineering :: Information Analysis
Classifier: Topic :: Software Development :: Libraries :: Python Modules
Requires-Dist: Pygments (==2.18.0)
Requires-Dist: SQLAlchemy (==2.0.30)
Requires-Dist: certifi (==2024.2.2)
Requires-Dist: charset-normalizer (==3.3.2)
Requires-Dist: click (==8.1.7)
Requires-Dist: colorama (==0.4.6)
Requires-Dist: contourpy (==1.2.1)
Requires-Dist: cycler (==0.12.1)
Requires-Dist: docutils (==0.21.2)
Requires-Dist: fonttools (==4.51.0)
Requires-Dist: greenlet (==3.0.3)
Requires-Dist: idna (==3.7)
Requires-Dist: importlib_metadata (==7.1.0)
Requires-Dist: joblib (==1.4.2)
Requires-Dist: keyring (==25.2.0)
Requires-Dist: kiwisolver (==1.4.5)
Requires-Dist: markdown-it-py (==3.0.0)
Requires-Dist: matplotlib (==3.8.4)
Requires-Dist: mdurl (==0.1.2)
Requires-Dist: more-itertools (==10.2.0)
Requires-Dist: nh3 (==0.2.17)
Requires-Dist: nltk (==3.8.1)
Requires-Dist: numpy (==1.26.4)
Requires-Dist: packaging (==24.0)
Requires-Dist: pandas (==2.2.2)
Requires-Dist: pillow (==10.3.0)
Requires-Dist: pkginfo (==1.10.0)
Requires-Dist: pyparsing (==3.1.2)
Requires-Dist: pyproject_hooks (==1.1.0)
Requires-Dist: python-dateutil (==2.9.0.post0)
Requires-Dist: pytz (==2024.1)
Requires-Dist: pywin32-ctypes (==0.2.2)
Requires-Dist: readme_renderer (==43.0)
Requires-Dist: regex (==2024.4.28)
Requires-Dist: requests (==2.31.0)
Requires-Dist: requests-toolbelt (==1.0.0)
Requires-Dist: rfc3986 (==2.0.0)
Requires-Dist: rich (==13.7.1)
Requires-Dist: scikit-learn (==1.4.2)
Requires-Dist: scipy (==1.13.0)
Requires-Dist: seaborn (==0.13.2)
Requires-Dist: six (==1.16.0)
Requires-Dist: threadpoolctl (==3.5.0)
Requires-Dist: tqdm (==4.66.4)
Requires-Dist: typing_extensions (==4.11.0)
Requires-Dist: tzdata (==2024.1)
Requires-Dist: urllib3 (==2.2.1)
Requires-Dist: zipp (==3.18.1)
Project-URL: Documentation, https://dataanalysistoolkit.readthedocs.io/en/latest/
Project-URL: Repository, https://github.com/thomasthaddeus/dataanalysistoolkit
